ligo_softioc/__init__.py
ligo_softioc/alarm.py
ligo_softioc/alarm_family.py
ligo_softioc/load_ioc.py
ligo_softioc/py.typed
ligo_softioc/soft_ioc.py
ligo_softioc/sorted_dict.py
ligo_softioc/util.py
ligo_softioc-0.1.7.dist-info/METADATA
ligo_softioc-0.1.7.dist-info/WHEEL
ligo_softioc-0.1.7.dist-info/licenses/COPYING
ligo_softioc-0.1.7.dist-info/licenses/LICENSE
ligo_softioc-0.1.7.dist-info/RECORD
