Metadata-Version: 2.3
Name: ligo-softioc
Version: 0.1.7
Summary: Support library for writing EPICS SoftIOCs in Python.
Project-URL: Homepage, https://git.ligo.org/cds/admin/softioc
Project-URL: Issues, https://git.ligo.org/cds/admin/softioc/-/issues
Author-email: Erik von Reis <evonreis@caltech.edu>
License-File: COPYING
License-File: LICENSE
Classifier: License :: OSI Approved :: GNU General Public License v3 (GPLv3)
Classifier: Operating System :: OS Independent
Classifier: Programming Language :: Python :: 3
Requires-Python: >=3.6
Requires-Dist: gpstime
Requires-Dist: pcaspy==0.7.3
